simple_pensando_dss/__init__.py
simple_pensando_dss/rest_client/LICENSE
simple_pensando_dss/rest_client/README
simple_pensando_dss/rest_client/__init__.py
simple_pensando_dss/rest_client/api.py
simple_pensando_dss/rest_client/decorators.py
simple_pensando_dss/rest_client/exceptions.py
simple_pensando_dss/rest_client/models.py
simple_pensando_dss/rest_client/request.py
simple_pensando_dss/rest_client/resource.py
simple_pensando_dss-0.2.dist-info/LICENSE
simple_pensando_dss-0.2.dist-info/METADATA
simple_pensando_dss-0.2.dist-info/WHEEL
simple_pensando_dss-0.2.dist-info/top_level.txt
simple_pensando_dss-0.2.dist-info/RECORD
