Metadata-Version: 2.1
Name: simple-pensando-dss
Version: 0.2
Summary: Simple REST-client for Pensando DSS PSM
Home-page: https://github.com/jinjamator/simple_pensando_dss
Author: Wilhelm Putz
Author-email: wp@aci.guru
License: ASL V2
Platform: UNKNOWN
Classifier: License :: OSI Approved :: Apache Software License
Classifier: Programming Language :: Python :: 3.7
Classifier: Programming Language :: Python :: 3.8
Classifier: Topic :: System :: Installation/Setup
Classifier: Topic :: System :: Systems Administration
Classifier: Topic :: Utilities
Requires-Python: >=3.7
License-File: LICENSE
